ValLocal/__init__.py
ValLocal/api.py
ValLocal/lock.py
ValLocal/parsing.py
ValLocal/structs.py
ValLocal/auth/__init__.py
ValLocal/auth/auth.py
ValLocal/auth/region.py
ValLocal-0.1.1.dist-info/LICENSE
ValLocal-0.1.1.dist-info/METADATA
ValLocal-0.1.1.dist-info/WHEEL
ValLocal-0.1.1.dist-info/top_level.txt
ValLocal-0.1.1.dist-info/RECORD
